gram_ai/__init__.py
gram_ai/_hooks/__init__.py
gram_ai/_hooks/registration.py
gram_ai/_hooks/sdkhooks.py
gram_ai/_hooks/types.py
gram_ai/_version.py
gram_ai/base.py
gram_ai/basesdk.py
gram_ai/environments.py
gram_ai/function_calling.py
gram_ai/httpclient.py
gram_ai/instances.py
gram_ai/langchain.py
gram_ai/models/__init__.py
gram_ai/models/apierror.py
gram_ai/models/canonicaltoolattributes.py
gram_ai/models/environment.py
gram_ai/models/environmententry.py
gram_ai/models/getinstanceop.py
gram_ai/models/getinstanceresult.py
gram_ai/models/getprompttemplateresult.py
gram_ai/models/gettemplateop.py
gram_ai/models/httptooldefinition.py
gram_ai/models/prompttemplate.py
gram_ai/models/rendertemplateop.py
gram_ai/models/rendertemplaterequestbody.py
gram_ai/models/rendertemplateresult.py
gram_ai/models/serviceerror.py
gram_ai/models/toolvariation.py
gram_ai/openai.py
gram_ai/openai_agents.py
gram_ai/py.typed
gram_ai/sdk.py
gram_ai/sdkconfiguration.py
gram_ai/templates.py
gram_ai/types/__init__.py
gram_ai/types/basemodel.py
gram_ai/utils/__init__.py
gram_ai/utils/annotations.py
gram_ai/utils/datetimes.py
gram_ai/utils/enums.py
gram_ai/utils/eventstreaming.py
gram_ai/utils/forms.py
gram_ai/utils/headers.py
gram_ai/utils/logger.py
gram_ai/utils/metadata.py
gram_ai/utils/queryparams.py
gram_ai/utils/requestbodies.py
gram_ai/utils/retries.py
gram_ai/utils/security.py
gram_ai/utils/serializers.py
gram_ai/utils/url.py
gram_ai/utils/values.py
gram_ai-0.3.2.dist-info/METADATA
gram_ai-0.3.2.dist-info/WHEEL
gram_ai-0.3.2.dist-info/RECORD
