Metadata-Version: 2.3
Name: gram-ai
Version: 0.3.2
Summary: Python Client SDK Generated by Speakeasy.
Author: GramAI
Requires-Python: >=3.9
Classifier: Programming Language :: Python :: 3
Classifier: Programming Language :: Python :: 3.9
Classifier: Programming Language :: Python :: 3.10
Classifier: Programming Language :: Python :: 3.11
Classifier: Programming Language :: Python :: 3.12
Classifier: Programming Language :: Python :: 3.13
Provides-Extra: langchain-core
Provides-Extra: openai
Provides-Extra: openai-agents
Requires-Dist: eval-type-backport (>=0.2.0)
Requires-Dist: httpx (>=0.28.1)
Requires-Dist: langchain-core (>=0.3.20) ; (python_version >= "3.9" and python_version < "4.0") and (extra == "langchain-core")
Requires-Dist: openai (>=1.70.0) ; extra == "openai"
Requires-Dist: openai-agents (>=0.0.10) ; extra == "openai-agents"
Requires-Dist: pydantic (>=2.11.2)
Requires-Dist: python-dateutil (>=2.8.2)
Requires-Dist: typing-inspection (>=0.4.0)
